jsondot/__init__.py
jsondot/jsondot.py
jsondot-0.9.0.dist-info/licenses/LICENSE
jsondot-0.9.0.dist-info/METADATA
jsondot-0.9.0.dist-info/WHEEL
jsondot-0.9.0.dist-info/top_level.txt
jsondot-0.9.0.dist-info/RECORD
