Metadata-Version: 2.4
Name: JsonDot
Version: 0.9.0
Summary: Load JSON files and use the data with dot notation then dump to the file
Home-page: https://github.com/Mits-Soft/JsonDot.git
Author: Marco Antonio Calviño Coira
Author-email: mits.soft.main@gmail.com
License: MIT
Classifier: Development Status :: 3 - Alpha
Classifier: License :: OSI Approved :: MIT License
Classifier: Programming Language :: Python :: 3.12
License-File: LICENSE
Dynamic: author
Dynamic: author-email
Dynamic: classifier
Dynamic: description
Dynamic: description-content-type
Dynamic: home-page
Dynamic: license
Dynamic: license-file
Dynamic: summary
